{
  "answered": true,
  "business_phone_number": "+19252386347",
  "customer_city": "Lee Vining",
  "customer_country": "US",
  "customer_name": "LEE VINING CA  ",
  "customer_phone_number": "+17602063092",
  "customer_state": "CA",
  "direction": "inbound",
  "duration": 14,
  "id": "CAL019b9a2d97997cdd819a498807ed19c8",
  "recording": "https://api.callrail.com/v3/a/ACC2572dc258af24a36a5f230a177c8820b/calls/CAL019b9a2d97997cdd819a498807ed19c8/recording",
  "recording_duration": 4,
  "recording_player": "https://app.callrail.com/calls/CAL019b9a2d97997cdd819a498807ed19c8/recording?access_key=2db76b6159f29dae40bc",
  "start_time": "2026-01-07T12:37:17.816-08:00",
  "tracking_phone_number": "+19253975463",
  "voicemail": false,
  "lead_score": null,
  "lead_explanation": null,
  "company_id": "COM1660768019b8465f836610da3a0e58d1",
  "company_name": "Rhino Builders",
  "transcription": "to avoid any suspension or verification issues.\n",
  "tags": [],
  "note": null,
  "source": "Lafayette GMB",
  "keywords": null,
  "campaign": null
}